LICENSE
README.md
pyhep.py
requirements.txt
setup.py
pyhep.egg-info/PKG-INFO
pyhep.egg-info/SOURCES.txt
pyhep.egg-info/dependency_links.txt
pyhep.egg-info/not-zip-safe
pyhep.egg-info/top_level.txt